py_stars_tools/__init__.py
py_stars_tools/encrypt_utils.py
py_stars_tools/regex_utils.py
py_stars_tools/time_tools.py
src/__init__.py
src/time_tools.py
py_stars_tools-0.0.6.dist-info/METADATA
py_stars_tools-0.0.6.dist-info/WHEEL
py_stars_tools-0.0.6.dist-info/top_level.txt
py_stars_tools-0.0.6.dist-info/RECORD
